LICENSE
README.md
pyproject.toml
setup.cfg
setup.py
infinite_campus/__init__.py
infinite_campus/assignments.py
infinite_campus/data.py
infinite_campus/district.py
infinite_campus/functions.py
infinite_campus/notifications.py
infinite_campus/students.py
infinite_campus/terms.py
infinite_campus/tools.py
infinite_campus.egg-info/PKG-INFO
infinite_campus.egg-info/SOURCES.txt
infinite_campus.egg-info/dependency_links.txt
infinite_campus.egg-info/top_level.txt