Metadata-Version: 2.1
Name: infinite-campus
Version: 1.0.0
Summary: API for Infinite Campus.
Home-page: https://github.com/pypa/sampleproject
Author: Nerd-Guy
Author-email: author@example.com
Project-URL: Bug Tracker, https://github.com/pypa/sampleproject/issues
Classifier: Programming Language :: Python :: 3
Classifier: License :: OSI Approved :: MIT License
Classifier: Operating System :: OS Independent
License-File: LICENSE
